{"projectdata":{"xapi":false,"scorm":false,"nextObjId":26,"name":"Test Scenario","description":"For Hardware Testing","category":"Other","version":1,"isscored":false,"cmi5":false,"xAPIActID":"https://cenariovr.com/17115","activityId":"https://cenariovr.com/17115","trial":false,"publishDate":"2021-09-09T18:04:37Z","fontsToLoad":["Roboto","Open Sans"]},"scenes":[{"name":"Start","assetId":"1a7ffe7f-6bdd-4d26-9f7e-aabd7364706e","src":null,"loop":false,"duration":60000,"actions":[{"action":null,"target":null,"conditions":null}],"actionsShow":[{"action":null,"target":null,"conditions":null}],"id":"1","assetName":"empty walls 360 background.jpeg","image":"scene/b982cf49-9741-4e34-b7ef-dd776ab33569.jpeg","objects":[{"type":"text","txt":"Welcome","name":"Card 1","visible":true,"fixed":false,"style":{"fontName":"Open Sans","fontColor":"rgb(0, 0, 0)","fontSize":"24pt","backColor":"rgba(78, 78, 78, 0)","opacity":0,"cardStyle":"rounded","align":"center"},"id":"2","varid":3,"pitch":8.594162879994451,"yaw":0,"offsetX":null,"offsetY":null,"distance":1,"rotation":{"x":0,"y":0,"z":0},"origWidth":0.23999976,"origHeight":0.085909005,"width":0.23999976,"height":0.085909005},{"type":"text","txt":"Press the play button to continue...","name":"Card 2","visible":true,"fixed":false,"style":{"fontName":"Open Sans","fontColor":"rgb(0, 0, 0)","fontSize":"18pt","backColor":"rgba(78, 78, 78, 0)","opacity":0,"cardStyle":"rounded","align":"center"},"id":"4","varid":5,"pitch":2.935478554583307,"yaw":0,"offsetX":null,"offsetY":null,"distance":1,"rotation":{"x":0,"y":0,"z":0}},{"name":"Continue","type":"hotspot","assetId":"0498c5bc-0abc-4d02-97c2-04550ad5498b","src":"media/eeba9327-3a6e-4f4f-b198-5fa6fcdb8b40.svg","visible":true,"fixed":true,"bTrans":false,"actions":[{"action":"link","target":"8","conditions":null}],"hoverin":[{"action":"animate","target":"this","animation":{"animType":"grow","size":0.3},"conditions":null}],"hoverout":[{"action":"animate","target":"this","animation":{"animType":"undo"},"conditions":null}],"assetName":"play.svg","assetColor":"#24AAEE","id":"6","varid":7,"origWidth":0.2715,"origHeight":0.2715,"width":0.24211585076494843,"height":0.24211585076494843,"pitch":null,"yaw":null,"offsetX":0.0008849557522123686,"offsetY":-0.3986074847693646,"distance":0,"rotation":{"x":0,"y":0,"z":0}},{"name":"Minimal Cool Logo","type":"audio","assetId":"328c5909-70d1-4d2f-baf9-a33dd8c3f159","src":"media/62b26da6-04c2-412d-a34f-de702ad9900f.mp3","visible":true,"fixed":false,"bTrans":false,"actions":[{"action":null,"target":null,"conditions":null}],"loop":false,"muted":false,"volume":1,"spatial":false,"assetName":"Minimal Cool Logo.mp3","id":"11","varid":12,"distance":1}]},{"name":"Test","assetId":"1332309b-cdfb-4abd-be46-ad27105837f1","src":null,"loop":false,"duration":60000,"actions":[{"action":null,"target":null,"conditions":null}],"actionsShow":[],"image":"scene/f53b41bd-46b9-42fd-a3da-a1e5c91ebd48.jpeg","assetName":"360 finished basement interior.jpeg","id":"8","objects":[{"type":"question","txt":"Test Question","correctchoice":null,"autohide":true,"visible":true,"fixed":true,"appearance":"question-card-numbered","choices":["Option 1","Option 2","Option 3"],"actions":[[{"action":"link","target":"15"}],[{"action":"link","target":"15"}],[{"action":"link","target":"15"}]],"style":{"fontName":"Open Sans","fontColor":"rgb(255, 255, 255)","fontSize":"18pt","backColor":"rgba(0, 0, 0, 0.9)","opacity":0.9,"cardStyle":"square","choiceFontColor":"#ffffff","choiceBackColor":"rgb(36, 170, 238)"},"name":"Question Test","id":"9","varid":10,"pitch":null,"yaw":null,"offsetX":0.0008849557522123686,"offsetY":0.00010841387120547746,"distance":0,"rotation":{"x":0,"y":0,"z":0},"origWidth":0.74999925,"origHeight":0.29454516,"width":0.74999925,"height":0.29454516}],"default_yaw":66.02343371087214},{"name":"3","assetId":"7ffd3571-d7e4-4ef6-880d-aa67aa2cd023","src":null,"loop":false,"duration":60000,"actions":[{"action":null,"target":null,"conditions":null}],"actionsShow":[],"image":"scene/8aff9cf0-37fa-4fbe-9288-b45336606ee7.jpg","assetName":"Modern apartment living room Custom.jpg","id":"15","objects":[{"type":"text","txt":"Finished!","name":"Info Card","visible":true,"fixed":true,"style":{"fontName":"Open Sans","fontColor":"rgb(0, 0, 0)","fontSize":"24pt","backColor":"rgba(255, 255, 255, 0.9)","opacity":0.9,"cardStyle":"square","align":"center"},"id":"16","varid":17,"pitch":null,"yaw":null,"offsetX":-0.00014900279766344449,"offsetY":0.22449483479356017,"distance":0,"rotation":{"x":0,"y":0,"z":0},"origWidth":0.23386340249999998,"origHeight":0.085909005,"width":0.23386340249999998,"height":0.085909005},{"name":"home","type":"hotspot","assetId":"3d91ee2e-a387-4c32-b105-3ab03c77facc","src":"media/7b48e016-49a5-47cd-9b4d-aedddb852561.svg","visible":true,"fixed":true,"bTrans":false,"actions":[{"action":"link","target":"1","conditions":null}],"hoverin":[{"action":"animate","target":"this","animation":{"animType":"grow","size":0.3},"conditions":null}],"hoverout":[{"action":"animate","target":"this","animation":{"animType":"undo"},"conditions":null}],"assetName":"home.svg","assetColor":"#24AAEE","id":"18","varid":19,"origWidth":0.2715,"origHeight":0.2715,"width":0.17106607102704063,"height":0.17106607102704063,"pitch":null,"yaw":null,"offsetX":-0.15944103819589356,"offsetY":-0.06758913522042853,"distance":0,"rotation":{"x":0,"y":0,"z":0}},{"name":"restart","type":"hotspot","assetId":"3787d907-e60f-4c92-ba36-cd9656f8a1ab","src":"media/cf290f0b-5d14-4430-a453-040d7c6f6895.svg","visible":true,"fixed":true,"bTrans":false,"actions":[{"action":"link","target":"8","conditions":null}],"hoverin":[{"action":"animate","target":"this","animation":{"animType":"grow","size":0.3},"conditions":null}],"hoverout":[{"action":"animate","target":"this","animation":{"animType":"undo"},"conditions":null}],"assetName":"restart.svg","assetColor":"#24AAEE","id":"20","varid":21,"origWidth":0.2715,"origHeight":0.2715,"width":0.17106607102704063,"height":0.17106607102704055,"pitch":null,"yaw":null,"offsetX":-0.00014900279766344449,"offsetY":-0.06758913522042853,"distance":0,"rotation":{"x":0,"y":0,"z":0}},{"name":"exit_to_app","type":"hotspot","assetId":"4527c5db-64a7-48cb-b57f-8ae97c3897c7","src":"media/548cafaa-bd0f-4f20-9e3c-f64bad9b1046.svg","visible":true,"fixed":true,"bTrans":false,"actions":[{"action":"exit","target":null,"conditions":null}],"hoverin":[{"action":"animate","target":"this","animation":{"animType":"grow","size":0.3},"conditions":null}],"hoverout":[{"action":"animate","target":"this","animation":{"animType":"undo"},"conditions":null}],"assetName":"exit_to_app.svg","assetColor":"#24AAEE","id":"22","varid":23,"origWidth":0.07200000000000001,"origHeight":0.07200000000000001,"width":0.17106607102704055,"height":0.17106607102704055,"pitch":null,"yaw":null,"offsetX":0.15752212389380538,"offsetY":-0.06758913522042853,"distance":0,"rotation":{"x":0,"y":0,"z":0}},{"name":"Interface UI 1 Ready","type":"audio","assetId":"7114d721-2d33-470a-aa25-8a3ea23ad45e","src":"media/726521d5-d7d8-485b-9fb9-8a41a40154ce.mp3","visible":true,"fixed":false,"bTrans":false,"actions":[{"action":null,"target":null,"conditions":null}],"loop":false,"muted":false,"volume":1,"spatial":false,"assetName":"Interface UI 1 Ready.mp3","id":"24","varid":25,"distance":1}],"default_yaw":23.343750690914227}]}